README.rst
setup.py
pyflogd/__init__.py
pyflogd/pyflogd.py
pyflogd.egg-info/PKG-INFO
pyflogd.egg-info/SOURCES.txt
pyflogd.egg-info/dependency_links.txt
pyflogd.egg-info/entry_points.txt
pyflogd.egg-info/requires.txt
pyflogd.egg-info/top_level.txt