Metadata-Version: 1.0
Name: pyflogd
Version: 0.1.1
Summary: File system access monitoring daemon
Home-page: UNKNOWN
Author: Maik Kulbe
Author-email: info@linux-web-development.de
License: MIT
Platform: UNKNOWN
